arcade_helpers/animated_sprite.py
arcade_helpers/key_manager.py
arcade_helpers/particles_collision.py
arcade_helpers/rotating_sprite.py
arcade_helpers-1.2.dist-info/LICENSE
arcade_helpers-1.2.dist-info/METADATA
arcade_helpers-1.2.dist-info/WHEEL
arcade_helpers-1.2.dist-info/top_level.txt
arcade_helpers-1.2.dist-info/RECORD
