Metadata-Version: 2.2
Name: arcade-helpers
Version: 1.2
Summary: Some helpers to work better/easier with the Arcade gaming library.
Author-email: Facundo Batista <facundo@taniquetil.com.ar>
License: Apache-2.0
Project-URL: Repository, https://github.com/facundobatista/arcade-helpers
Keywords: arcade,game-development,graphics
Classifier: Development Status :: 4 - Beta
Classifier: Intended Audience :: Developers
Classifier: License :: OSI Approved :: Apache Software License
Classifier: Programming Language :: Python :: 3
Classifier: Topic :: Software Development :: Libraries :: Python Modules
Requires-Python: >=3.10
License-File: LICENSE
Requires-Dist: arcade>=3
